mlproject/__init__.py
mlproject/distance.py
mlproject/lib.py
mlproject/data/.keep
mlproject-1.0.data/scripts/mlproject-distance
mlproject-1.0.data/scripts/mlproject-run
tests/__init__.py
tests/test_distance.py
tests/test_lib.py
mlproject-1.0.dist-info/METADATA
mlproject-1.0.dist-info/WHEEL
mlproject-1.0.dist-info/top_level.txt
mlproject-1.0.dist-info/RECORD
