Metadata-Version: 2.1
Name: mlproject
Version: 1.0
Summary: Project Description
Home-page: UNKNOWN
Author: UNKNOWN
Author-email: UNKNOWN
License: UNKNOWN
Platform: UNKNOWN
Requires-Dist: pip (>=9)
Requires-Dist: setuptools (>=26)
Requires-Dist: twine
Requires-Dist: wheel (>=0.29)
Requires-Dist: numpy
Requires-Dist: pandas
Requires-Dist: scikit-learn
Requires-Dist: black
Requires-Dist: coverage
Requires-Dist: flake8
Requires-Dist: pytest
Requires-Dist: yapf
Requires-Dist: gcsfs
Requires-Dist: google-cloud-storage
Requires-Dist: mlflow
Requires-Dist: s3fs
Requires-Dist: six (>=1.14)
Requires-Dist: joblib
Requires-Dist: memoized-property
Requires-Dist: termcolor
